README.md
setup.cfg
setup.py
NCP_CSS/CSS.py
NCP_CSS/__init__.py
NCP_CSS.egg-info/PKG-INFO
NCP_CSS.egg-info/SOURCES.txt
NCP_CSS.egg-info/dependency_links.txt
NCP_CSS.egg-info/requires.txt
NCP_CSS.egg-info/top_level.txt
test/CSS_Test.py
test/__init__.py