Metadata-Version: 1.2
Name: NCP-CSS
Version: 0.14
Summary: This is for CSS(Clova Speech Synthesis) service of NAVER Cloud Platform	https://github.com/ultimatelife/NCP_CSS
Home-page: https://github.com/ultimatelife/NCP_CSS.git
Author: geonwoo.kim
Author-email: drama0708@gmail.com
License: Naver Cloud Platform
Keywords: NCP,Papago,Clova,clova,CSS
Platform: UNKNOWN
Classifier: Programming Language :: Python :: 3.6
Requires-Python: >=3.6
